odvm/__init__.py
odvm-0.1.1.dist-info/METADATA
odvm-0.1.1.dist-info/WHEEL
odvm-0.1.1.dist-info/top_level.txt
odvm-0.1.1.dist-info/RECORD
