Metadata-Version: 2.4
Name: odvm
Version: 0.1.1
Summary: Open, Dynamic, and Versatile Modeling AutoML system package
Home-page: https://github.com/omnia197/odvm
Author: Omnia Ayman
Author-email: Omnia Ayman <omnia81ayman@gmail.com>
Project-URL: Homepage, https://github.com/omnia197/odvm
Requires-Python: >=3.8
Requires-Dist: pandas>=1.0
Requires-Dist: scikit-learn
Requires-Dist: xgboost
Requires-Dist: lightgbm
Requires-Dist: catboost
Requires-Dist: dask[dataframe]
Requires-Dist: fastapi
Requires-Dist: uvicorn
